makemd/__init__.py
makemd/__main__.py
makemd/add_section.py
makemd/clean_yaml_refs.py
makemd/dependencies.py
makemd/extractdate_talk.py
makemd/flags.py
makemd/makecv.py
makemd/makedependency_talk.py
makemd/makediagdependency_talk.py
makemd/maketalk.py
makemd/mdfield.py
makemd/mdlist.py
makemd/mdpp.py
makemd/ndlml.py
makemd-0.1.0.dist-info/METADATA
makemd-0.1.0.dist-info/WHEEL
makemd-0.1.0.dist-info/dependency_links.txt
makemd-0.1.0.dist-info/entry_points.txt
makemd-0.1.0.dist-info/top_level.txt
makemd-0.1.0.dist-info/RECORD
