Metadata-Version: 2.1
Name: makemd
Version: 0.1.0
Summary: Package for converting collection of markdown files and macros into talks and notes.
Home-page: https://github.com/lawrennd/makemd
Author: Neil D. Lawrence
Author-email: lawrennd@gmail.com
License: MIT
Platform: UNKNOWN
Classifier: License :: OSI Approved :: MIT License
Classifier: Programming Language :: Python
Classifier: Programming Language :: Python :: 3
Classifier: Programming Language :: Python :: 3.6
Classifier: Programming Language :: Python :: Implementation :: CPython
Classifier: Programming Language :: Python :: Implementation :: PyPy
Requires-Python: >=3.6.0
Requires-Dist: ndlpy
Requires-Dist: python-frontmatter
Requires-Dist: pandas
